grapapy.cp313-win_amd64.pyd
grapapy-0.1.52/grapa_static.lib
grapapy-0.1.52.dist-info/licenses/LICENSE
grapapy-0.1.52.dist-info/METADATA
grapapy-0.1.52.dist-info/WHEEL
grapapy-0.1.52.dist-info/top_level.txt
grapapy-0.1.52.dist-info/RECORD
