Metadata-Version: 2.4
Name: grapapy
Version: 0.1.52
Summary: GrapaPy brings robust, production-ready parallel ETL/data processing to Python. By leveraging Grapa's C++ backend, GrapaPy enables true parallelism for high-throughput data workflows—bypassing Python's GIL and making advanced data processing simple and fast.
Home-page: https://grapa-dev.github.io/grapa/
Author: Chris Matichuk
Author-email: matichuk@hotmail.com
Requires-Python: >=3.6
License-File: LICENSE
Dynamic: author
Dynamic: author-email
Dynamic: description
Dynamic: description-content-type
Dynamic: home-page
Dynamic: license-file
Dynamic: requires-python
Dynamic: summary
